{
  "main": {
    "id": "ba9a5ea1e8618089",
    "type": "split",
    "children": [
      {
        "id": "4f54f89d5e7e602f",
        "type": "tabs",
        "children": [
          {
            "id": "f4debffc321fb010",
            "type": "leaf",
            "state": {
              "type": "markdown",
              "state": {
                "file": "Term 2/Week 1.md",
                "mode": "source",
                "source": false
              },
              "icon": "lucide-file",
              "title": "Week 1"
            }
          }
        ]
      }
    ],
    "direction": "vertical"
  },
  "left": {
    "id": "80aa4af6ec89f39e",
    "type": "split",
    "children": [
      {
        "id": "82cdaad15fb151c1",
        "type": "tabs",
        "children": [
          {
            "id": "4a098a4b51fe9d6a",
            "type": "leaf",
            "state": {
              "type": "file-explorer",
              "state": {
                "sortOrder": "alphabetical",
                "autoReveal": false
              },
              "icon": "lucide-folder-closed",
              "title": "Files"
            }
          },
          {
            "id": "471171546b6c96e9",
            "type": "leaf",
            "state": {
              "type": "search",
              "state": {
                "query": "",
                "matchingCase": false,
                "explainSearch": false,
                "collapseAll": false,
                "extraContext": false,
                "sortOrder": "alphabetical"
              },
              "icon": "lucide-search",
              "title": "Search"
            }
          },
          {
            "id": "8c37624684ae47f1",
            "type": "leaf",
            "state": {
              "type": "bookmarks",
              "state": {},
              "icon": "lucide-bookmark",
              "title": "Bookmarks"
            }
          }
        ]
      }
    ],
    "direction": "horizontal",
    "width": 200
  },
  "right": {
    "id": "a024a3df447707a7",
    "type": "split",
    "children": [
      {
        "id": "e0b276fa5363e476",
        "type": "tabs",
        "children": [
          {
            "id": "abeadf8a39dcedec",
            "type": "leaf",
            "state": {
              "type": "backlink",
              "state": {
                "file": "Term 1/Week 1.md",
                "collapseAll": false,
                "extraContext": false,
                "sortOrder": "alphabetical",
                "showSearch": false,
                "searchQuery": "",
                "backlinkCollapsed": false,
                "unlinkedCollapsed": true
              },
              "icon": "links-coming-in",
              "title": "Backlinks for Week 1"
            }
          },
          {
            "id": "91d8a4db14f2df7c",
            "type": "leaf",
            "state": {
              "type": "outgoing-link",
              "state": {
                "file": "Term 1/Week 1.md",
                "linksCollapsed": false,
                "unlinkedCollapsed": true
              },
              "icon": "links-going-out",
              "title": "Outgoing links from Week 1"
            }
          },
          {
            "id": "8a64fa685d7c880c",
            "type": "leaf",
            "state": {
              "type": "tag",
              "state": {
                "sortOrder": "frequency",
                "useHierarchy": true,
                "showSearch": false,
                "searchQuery": ""
              },
              "icon": "lucide-tags",
              "title": "Tags"
            }
          },
          {
            "id": "57293c5045dc71ce",
            "type": "leaf",
            "state": {
              "type": "outline",
              "state": {
                "file": "Term 1/Week 1.md",
                "followCursor": false,
                "showSearch": false,
                "searchQuery": ""
              },
              "icon": "lucide-list",
              "title": "Outline of Week 1"
            }
          }
        ]
      }
    ],
    "direction": "horizontal",
    "width": 300,
    "collapsed": true
  },
  "left-ribbon": {
    "hiddenItems": {
      "switcher:Open quick switcher": false,
      "graph:Open graph view": false,
      "canvas:Create new canvas": false,
      "daily-notes:Open today's daily note": false,
      "templates:Insert template": false,
      "command-palette:Open command palette": false,
      "bases:Create new base": false
    }
  },
  "active": "f4debffc321fb010",
  "lastOpenFiles": [
    "Term 1/Week 5.md",
    "Term 1/Week 6.md",
    "Term 1/Week 7.md",
    "Term 1/Week 8.md",
    "Term 1/Term 1 Logbook.pdf",
    "Term 1/Week 9.md",
    "Term 1/Week 10.md",
    "Term 1/Term 1 Logbook_compressed.pdf",
    "Term 2/Christmas Holidays.pdf",
    "Term 2/Christmas Holidays.md",
    "Term 2/Week 1.md",
    "Term 1/Git History.md",
    "Term 1/Week 4.md",
    "Term 1/Week 3.md",
    "Term 1/Week 1.md",
    "Term 1/Term 1 Logbook.md",
    "Term 2/Derivations/Christmas Holidays/Escher in the Sky/(9) Derived Potential for W=muS.png",
    "Term 2/Derivations/Christmas Holidays/Escher in the Sky/Derived Potential for W=muS.png",
    "Term 2/Derivations/Christmas Holidays/Escher in the Sky/(7) General solution with axion part 1.png",
    "Term 2/Derivations/Christmas Holidays/Escher in the Sky/(8) General solution with axion part 2.png",
    "Term 2/Derivations/Christmas Holidays/Escher in the Sky/(7) General solution with axion.png",
    "Term 2/Derivations/Christmas Holidays/Escher in the Sky/(6) Kinetic Lagragian Fixed direction.png",
    "Term 2/Derivations/Christmas Holidays/Escher in the Sky/(5) F-term potential mu S part 3.png",
    "Term 2/Derivations/Christmas Holidays/Escher in the Sky/(4) F-term potential mu S part 2.png",
    "Term 2/Derivations/Christmas Holidays/Escher in the Sky/(3) F-term potential mu S part 1.png",
    "Term 2/Derivations/Christmas Holidays/Escher in the Sky/(2) Kahler metric part 2.png",
    "Term 2/Derivations/Christmas Holidays/Escher in the Sky/IMG_1278.HEIC",
    "Term 2/Derivations/Christmas Holidays/Escher in the Sky/IMG_1279.HEIC",
    "Term 2/Derivations/Christmas Holidays/Escher in the Sky/IMG_1280.HEIC",
    "Term 2/Derivations/Christmas Holidays/Escher in the Sky",
    "Term 2/Derivations/Week 1",
    "Term 2/Derivations/untitled folder",
    "Term 2/Derivations/Christmas Holidays",
    "Term 2/Derivations/Escher in the Sky/(2) Fterm potential derivation part 2.md",
    "Term 1/Week 2.md",
    "Term 1/().md",
    "Term 1/Github.md",
    "Derivations/Term 1/Week 1/(10).heic.md",
    "Term 1/(6), (7) part 1.heic.md",
    "Attachments/Derivations/Term.md",
    "_templates/weekly_template.md",
    "_templates/daily_subheadings.md"
  ]
}